figtion/__doc__
figtion/__init__.py
figtion-1.1.1.dist-info/LICENSE
figtion-1.1.1.dist-info/METADATA
figtion-1.1.1.dist-info/WHEEL
figtion-1.1.1.dist-info/top_level.txt
figtion-1.1.1.dist-info/RECORD
