Metadata-Version: 2.1
Name: figtion
Version: 1.1.1
Summary: A simple configuration interface with plaintext and encrypted file support.
Home-page: https://github.com/dactylroot/figtion
Download-URL: https://github.com/dactylroot/figtion/archive/1.1.1.tar.gz
Author: Cory Root
Author-email: dactylroot@gmail.com
License: MIT
Keywords: configuration secret raspberry pi embedded iot
Classifier: Development Status :: 5 - Production/Stable
Classifier: License :: OSI Approved :: MIT License
Classifier: Programming Language :: Python :: 3
Classifier: Topic :: Home Automation
Classifier: Topic :: Software Development :: Embedded Systems
Classifier: Topic :: Security
Classifier: Topic :: Security :: Cryptography
Requires-Python: >=3.5
License-File: LICENSE
Requires-Dist: pyyaml
Requires-Dist: pynacl
